nnlite
