Metadata-Version: 2.1
Name: nnlite
Version: 0.0.3
Summary: Some utilities and wrappers for Neural Network Models
Home-page: https://github.com/huangyh09/nnlite
Author: ['nnlite team']
Author-email: yuanhua@hku.hk
License: Apache-2.0
Keywords: Neural Network Models,Machine Learning
License-File: LICENSE
Requires-Dist: numpy>=1.9.0
Requires-Dist: scipy>=1.4.0
Requires-Dist: matplotlib
Requires-Dist: pandas
Requires-Dist: scikit-learn
Requires-Dist: torch
Requires-Dist: tqdm
Provides-Extra: docs
Requires-Dist: sphinx_bootstrap_theme; extra == "docs"
